resourcegeo/__init__.py
resourcegeo/base/__init__.py
resourcegeo/base/basedata.py
resourcegeo/base/utilities.py
resourcegeo/base/base_data/assay_geo.csv
resourcegeo/base/base_data/bm.csv
resourcegeo/base/base_data/collar.csv
resourcegeo/blockmodel/__init__.py
resourcegeo/blockmodel/blockmodel.py
resourcegeo/blockmodel/flatten.py
resourcegeo/drillholes/__init__.py
resourcegeo/drillholes/integrity.py
resourcegeo/drillholes/split_interval.py
resourcegeo/drillholes/utilities.py
resourcegeo/plots/__init__.py
resourcegeo/plots/boxplots.py
resourcegeo/plots/deviation.py
resourcegeo/plots/drilling.py
resourcegeo/plots/homotopic_scatter.py
resourcegeo/plots/probability_plot.py
resourcegeo/plots/qqplot.py
resourcegeo/plots/tongrad.py
resourcegeo/plots/utilities.py
resourcegeo/statistics/__init__.py
resourcegeo/statistics/cdf.py
resourcegeo/statistics/table_statistics.py
resourcegeo/statistics/utilities.py
resourcegeo/transformation/__init__.py
resourcegeo/transformation/capping.py
resourcegeo-0.1.9.dist-info/License.md
resourcegeo-0.1.9.dist-info/METADATA
resourcegeo-0.1.9.dist-info/WHEEL
resourcegeo-0.1.9.dist-info/top_level.txt
resourcegeo-0.1.9.dist-info/RECORD
