Metadata-Version: 2.1
Name: resourcegeo
Version: 0.1.9
Summary: Python package for resource geologists
Author: Harold Velasquez S.
Author-email: hgvelasq@ualberta.ca
Classifier: License :: OSI Approved :: MIT License
Classifier: Programming Language :: Python :: 3
Requires-Python: >3.7.6,<3.8
License-File: License.md
Requires-Dist: matplotlib (==3.5.3)
Requires-Dist: numpy (==1.21.6)
Requires-Dist: pandas (==1.3.5)
Requires-Dist: probscale (==0.2.5)
Requires-Dist: scipy (==1.7.3)
Requires-Dist: setuptools (==65.6.3)
Requires-Dist: sphinx-rtd-theme (==1.2.2)
Requires-Dist: tqdm (==4.66.1)
